README.rst
setup.py
reconf/__init__.py
reconf/config.py
reconf/location.py
reconf/loggingconfig.py
reconf/settings.py
reconf.egg-info/PKG-INFO
reconf.egg-info/SOURCES.txt
reconf.egg-info/dependency_links.txt
reconf.egg-info/requires.txt
reconf.egg-info/top_level.txt