Metadata-Version: 1.1
Name: reconf
Version: 0.1.4
Summary: Reloadable configuration settings.
Home-page: http://github.com/gilesbrown/reconf
Author: Giles Brown
Author-email: giles_brown@hotmail.com
License: BSD
Download-URL: http://github.com/gilesbrown/reconf/tarball/0.1.4
Platform: UNKNOWN
Classifier: Development Status :: 3 - Alpha
Classifier: Intended Audience :: Developers
Classifier: Natural Language :: English
Classifier: License :: OSI Approved :: BSD License
Classifier: Programming Language :: Python
Classifier: Programming Language :: Python :: 2.7
